minhook/MinHook.x64.dll
minhook/MinHook.x86.dll
minhook/__init__.py
minhook/hook.py
pyminhook-0.1.dist-info/METADATA
pyminhook-0.1.dist-info/WHEEL
pyminhook-0.1.dist-info/top_level.txt
pyminhook-0.1.dist-info/RECORD
