Metadata-Version: 2.1
Name: pyminhook
Version: 0.1
Summary: MinHook warp of Python
Home-page: https://github.com/howmp/pyminhook
Author: howmp
Author-email: zhaopeiyuan6@gmail.com
License: MIT
Platform: UNKNOWN
Requires-Python: >=3.7
